apogeebrain/__init__.py
apogeebrain/ann.py
apogeebrain/fitting.py
apogeebrain/monte.py
apogeebrain/monte4.py
apogeebrain/utils.py
apogeebrain/data/apStar-dr17-2M17335483-2753043.fits
apogeebrain/data/apStar-dr17-2M19485057+5005279.fits
apogeebrain/data/apVisit-r13-5095-55844-128.fits
apogeebrain/data/apVisit-r13-9518-57729-104.fits
apogeebrain/data/apogeedr17_rgb_feh_ann.npz
apogeebrain/data/apogeedr17_rgb_logg_ann.npz
apogeebrain-1.0.1.data/scripts/apogeebrain
apogeebrain-1.0.1.dist-info/licenses/LICENSE
apogeebrain-1.0.1.dist-info/METADATA
apogeebrain-1.0.1.dist-info/WHEEL
apogeebrain-1.0.1.dist-info/top_level.txt
apogeebrain-1.0.1.dist-info/RECORD
