Metadata-Version: 2.4
Name: apogeebrain
Version: 1.0.1
Summary: Abundance determination of APOGEE spectra using neural network emulator
Home-page: https://github.com/dnidever/apogeebrain
Author: David Nidever
Author-email: David Nidever <dnidever@montana.edu>
Maintainer-email: David Nidever <dnidever@montana.edu>
License: MIT License
Project-URL: Documentation, https://apogeebrain.readthedocs.org
Project-URL: Repository, https://github.com/dnidever/apogeebrain
Keywords: spectra,abundances,stars
Classifier: Development Status :: 3 - Alpha
Classifier: License :: OSI Approved :: MIT License
Classifier: Programming Language :: Python
Requires: numpy
Requires: astropy(>=4.0)
Requires: scipy
Requires: dlnpyutils
Requires: doppler
Requires: theborg
Requires: gdown
Requires-Python: >=3.9
License-File: LICENSE
Requires-Dist: scipy
Requires-Dist: numpy
Requires-Dist: matplotlib
Requires-Dist: astropy
Requires-Dist: dill
Requires-Dist: dlnpyutils
Requires-Dist: emcee
Requires-Dist: corner
Requires-Dist: gdown
Provides-Extra: gui
Requires-Dist: PyQt5; extra == "gui"
Provides-Extra: cli
Requires-Dist: rich; extra == "cli"
Requires-Dist: click; extra == "cli"
Dynamic: author
Dynamic: home-page
Dynamic: license-file
Dynamic: requires
